nanoatp/__init__.py
nanoatp/bskyagent.py
nanoatp/richtext.py
nanoatp-0.4.1.dist-info/LICENSE
nanoatp-0.4.1.dist-info/METADATA
nanoatp-0.4.1.dist-info/WHEEL
nanoatp-0.4.1.dist-info/RECORD
