Metadata-Version: 2.1
Name: nanoatp
Version: 0.4.1
Summary: A nano implementation of the AT Protocol for Python.
Home-page: https://github.com/susumuota/nanoatp
License: MIT
Keywords: atprotocol,atproto,bluesky
Author: Susumu OTA
Author-email: 1632335+susumuota@users.noreply.github.com
Requires-Python: >=3.9,<4.0
Classifier: License :: OSI Approved :: MIT License
Classifier: Programming Language :: Python :: 3
Classifier: Programming Language :: Python :: 3.9
Classifier: Programming Language :: Python :: 3.10
Classifier: Programming Language :: Python :: 3.11
Classifier: Topic :: Software Development :: Libraries :: Python Modules
Requires-Dist: requests (>=2.31.0,<3.0.0)
Requires-Dist: tld (>=0.13,<0.14)
Project-URL: Documentation, https://github.com/susumuota/nanoatp#readme
Project-URL: Repository, https://github.com/susumuota/nanoatp
